apksearch/__init__.py
apksearch/entities.py
apksearch/parsing.py
apksearch/search.py
tests/__init__.py
tests/test_parsing.py
tests/test_search.py
APKMirror_Search-1.0.1.dist-info/LICENSE
APKMirror_Search-1.0.1.dist-info/METADATA
APKMirror_Search-1.0.1.dist-info/WHEEL
APKMirror_Search-1.0.1.dist-info/top_level.txt
APKMirror_Search-1.0.1.dist-info/RECORD
